LICENSE
MANIFEST.in
README.md
setup.py
Ramen.egg-info/PKG-INFO
Ramen.egg-info/SOURCES.txt
Ramen.egg-info/dependency_links.txt
Ramen.egg-info/requires.txt
Ramen.egg-info/top_level.txt
ramen/__init__.py
ramen/admin.py
ramen/boot.py
ramen/decorators.py
ramen/forms.py
ramen/handlers.py
ramen/jinja2htmlcompress.py
ramen/pjs.py
ramen/rules.py
ramen/security.py
ramen/trigger.py
ramen/urls.py
ramen/views.py
ramen.egg-info/SOURCES.txt
ramen/bin/ramen
ramen/db/__init__.py
ramen/db/fields.py
ramen/db/proxy.py
ramen/db/query.py
ramen/db/record.py
ramen/mimemail/__init__.py
ramen/mimemail/mail.py
ramen/mimemail/misc.py
ramen/mimemail/parts.py
ramen/templates/.DS_Store
ramen/templates/__init__.py
ramen/templates/project/__init__.py
ramen/templates/project/settings.py
ramen/templates/project/assets/__init__.py
ramen/templates/project/core/__init__.py
ramen/templates/project/custom/__init__.py
ramen/templates/project/handlers/__init__.py
ramen/templates/project/models/__init__.py
ramen/templates/project/routes/__init__.py