Metadata-Version: 1.1
Name: ramen
Version: 0.0.2
Summary: Tornado based simple web framework
Home-page: http://gorskiy.kz/ramen
Author: Anton Gorskiy
Author-email: gorskiy.anton@gmail.com
License: Apache v2
Platform: UNKNOWN
Classifier: Development Status :: 2 - Pre-Alpha
Classifier: Intended Audience :: Developers
Classifier: License :: OSI Approved :: MIT License
Classifier: Programming Language :: Python :: 2.6
Classifier: Programming Language :: Python :: 2.7
Classifier: Topic :: Internet :: WWW/HTTP :: HTTP Servers
